gcpds/distutils/__init__.py
gcpds/distutils/distutils.py
gcpds/distutils/notebooks_template/readme.ipynb
gcpds/distutils/notebooks_template/refs.bib
gcpds/distutils/notebooks_template/.ipynb_checkpoints/readme-checkpoint.ipynb
gcpds/distutils/project_template/LICENSE.txt.j2
gcpds/distutils/project_template/MANIFEST.in
gcpds/distutils/project_template/dot.gitignore
gcpds/distutils/project_template/dot.readthedocs.yml
gcpds/distutils/project_template/setup.py.j2
gcpds/distutils/project_template/gcpds/{{PKG_NAME}}/__init__.py
gcpds/distutils/sphinx_template/Makefile_t
gcpds/distutils/sphinx_template/conf.py_t
gcpds/utils/__init__.py
gcpds/utils/colab.py
gcpds/utils/mne_handler.py
gcpds/utils/processing.py
gcpds/utils/visualizations.py
gcpds/utils/distutils/__init__.py
gcpds/utils/distutils/distutils.py
gcpds/utils/distutils/template/LICENSE.txt.j2
gcpds/utils/distutils/template/MANIFEST.in
gcpds/utils/distutils/template/README.md.j2
gcpds/utils/distutils/template/dot.gitignore
gcpds/utils/distutils/template/dot.readthedocs.yml
gcpds/utils/distutils/template/setup.py.j2
gcpds/utils/distutils/template/docs/Makefile.j2
gcpds/utils/distutils/template/docs/requirements.txt
gcpds/utils/distutils/template/docs/source/conf.py.j2
gcpds/utils/distutils/template/docs/source/index.rst
gcpds/utils/distutils/template/docs/source/refs.bib
gcpds/utils/distutils/template/docs/source/_static/custom.css
gcpds/utils/distutils/template/docs/source/_templates/sidebar.html
gcpds/utils/distutils/template/docs/source/notebooks/jupiterlab.sh
gcpds/utils/distutils/template/docs/source/notebooks/readme.ipynb.j2
gcpds/utils/distutils/template/gcpds/{{PKG_NAME}}/__init__.py
gcpds/utils/loaddb/__init__.py
gcpds/utils/loaddb/base.py
gcpds/utils/loaddb/databases.py
gcpds/utils/loaddb/fids.json
gcpds/utils/loaddb/fids.json.old
gcpds/utils/loaddb/fids.json.orig
gcpds/utils/loaddb/google_drive_downloader.py
gcpds/utils/loaddb/loaddb.py
gcpds_utils-0.1a7.data/scripts/gcpds_distutils
gcpds_utils-0.1a7.dist-info/LICENSE.txt
gcpds_utils-0.1a7.dist-info/METADATA
gcpds_utils-0.1a7.dist-info/WHEEL
gcpds_utils-0.1a7.dist-info/top_level.txt
gcpds_utils-0.1a7.dist-info/RECORD
